bitepimodule.cpython-37m-darwin.so
bitepi/__init__.py
bitepi/bitepi.py
bitepi/version.py
bitepi-0.1.8.dist-info/LICENSE.txt
bitepi-0.1.8.dist-info/METADATA
bitepi-0.1.8.dist-info/WHEEL
bitepi-0.1.8.dist-info/top_level.txt
bitepi-0.1.8.dist-info/RECORD
