Metadata-Version: 2.1
Name: bitepi
Version: 0.1.8
Summary: Python wrapper for the BitEpi program, for finding epistasisinteractions
Home-page: https://github.com/bhosking/bitepi-python
Author: Brendan Hosking
Author-email: brendan.hosking@csiro.au
License: UNKNOWN
Download-URL: https://github.com/bhosking/bitepi-python/archive/v0.1.8.tar.gz
Keywords: BIONINFORMATICS,EPISTASIS
Platform: UNKNOWN
Classifier: Development Status :: 4 - Beta
Classifier: Intended Audience :: Science/Research
Classifier: License :: Other/Proprietary License
Classifier: Operating System :: POSIX
Classifier: Programming Language :: Python :: 3 :: Only
Classifier: Topic :: Scientific/Engineering :: Bio-Informatics
Requires-Python: >=3
Requires-Dist: numpy
Requires-Dist: pandas
